CHANGES.txt
CONTRIBUTORS.txt
MANIFEST.in
README.txt
setup.cfg
setup.py
docs/Makefile
docs/source/conf.py
docs/source/index.rst
docs/source/_themes/bootstrap/globaltoc.html
docs/source/_themes/bootstrap/index.html
docs/source/_themes/bootstrap/layout.html
docs/source/_themes/bootstrap/localtoc.html
docs/source/_themes/bootstrap/relations.html
docs/source/_themes/bootstrap/searchbox.html
docs/source/_themes/bootstrap/source.html
docs/source/_themes/bootstrap/theme.conf
docs/source/_themes/bootstrap/static/bootstrap-sphinx.css_t
docs/source/_themes/bootstrap/static/bootstrap.min.js
docs/source/_themes/bootstrap/static/jquery.js
docs/source/_themes/bootstrap/static/css/bootstrap-responsive.min.css
docs/source/_themes/bootstrap/static/css/bootstrap.min.css
docs/source/_themes/bootstrap/static/img/glyphicons-halflings-white.png
docs/source/_themes/bootstrap/static/img/glyphicons-halflings.png
docs/source/authoring/conversions.rst
docs/source/authoring/conversions_center.rst
docs/source/authoring/installation.rst
docs/source/authoring/manage_content.rst
docs/source/authoring/supplementary.rst
docs/source/authoring/images/add-aggregator.png
docs/source/authoring/images/add-image.png
docs/source/authoring/images/ae_install_plone.png
docs/source/authoring/images/ae_install_zmi.png
docs/source/authoring/images/calibre_add_form.png
docs/source/authoring/images/calibre_view_form.png
docs/source/authoring/images/cc_content_folder.png
docs/source/authoring/images/cc_inspector_anchors.png
docs/source/authoring/images/cc_inspector_document_structure.png
docs/source/authoring/images/cc_inspector_image.png
docs/source/authoring/images/cc_inspector_links.png
docs/source/authoring/images/cc_inspectors.png
docs/source/authoring/images/cc_more_details.png
docs/source/authoring/images/cc_more_details_view.png
docs/source/authoring/images/cc_transformations.png
docs/source/authoring/images/cc_view.png
docs/source/authoring/images/download-as-zip.png
zopyx.authoring.egg-info/PKG-INFO
zopyx.authoring.egg-info/SOURCES.txt
zopyx.authoring.egg-info/dependency_links.txt
zopyx.authoring.egg-info/entry_points.txt
zopyx.authoring.egg-info/namespace_packages.txt
zopyx.authoring.egg-info/not-zip-safe
zopyx.authoring.egg-info/paster_plugins.txt
zopyx.authoring.egg-info/requires.txt
zopyx.authoring.egg-info/top_level.txt
