Metadata-Version: 1.0
Name: zopyx.authoring
Version: 2.4.0
Summary: Produce & Publish Authoring Environment
Home-page: http://www.produce-and-publish.com
Author: Andreas Jung
Author-email: info@zopyx.com
License: GNU Public License V2 (GPL 2)
Platform: UNKNOWN
Classifier: Framework :: Plone
Classifier: Framework :: Plone :: 4.1
Classifier: Framework :: Plone :: 4.2
Classifier: Intended Audience :: Developers
Classifier: License :: OSI Approved :: GNU General Public License (GPL)
